srscloud_integration/__init__.py
srscloud_integration/exemplo_tarefa.py
srscloud_integration/srscloud_integration.py
srscloud_integration-0.4.0.dist-info/licenses/LICENSE.md
srscloud_integration-0.4.0.dist-info/METADATA
srscloud_integration-0.4.0.dist-info/WHEEL
srscloud_integration-0.4.0.dist-info/top_level.txt
srscloud_integration-0.4.0.dist-info/RECORD
