Metadata-Version: 2.4
Name: srscloud-integration
Version: 0.4.0
Summary: Integração com SRS-Cloud para automação de processos.
Author-email: Automate Brasil <cx@automate.com>
License-Expression: CC-BY-NC-4.0
Project-URL: Homepage, https://github.com/Automate-Brasil/srscloud-integration
Project-URL: Bug Tracker, https://github.com/Automate-Brasil/srscloud-integration/issues
Classifier: Programming Language :: Python :: 3
Classifier: Operating System :: OS Independent
Classifier: Topic :: Software Development :: Libraries :: Python Modules
Requires-Python: >=3.8
License-File: LICENSE.md
Requires-Dist: requests
Requires-Dist: urllib3
Dynamic: license-file
